pytour-3.0.0.dist-info/licenses/LICENSE
tour/__init__.py
tour/artifacts_removal.py
tour/backend.py
tour/package_manage.py
tour/torch_trainer.py
tour/vis.py
tour/dataclass/__init__.py
tour/dataclass/dataset.py
tour/dataclass/io.py
tour/dataclass/stim.py
pytour-3.0.0.dist-info/METADATA
pytour-3.0.0.dist-info/WHEEL
pytour-3.0.0.dist-info/top_level.txt
pytour-3.0.0.dist-info/RECORD
